pycassodicom/__init__.py
pycassodicom/black_out.py
pycassodicom/blackout_factory.py
pycassodicom/update_dicom_tags.py
pycassodicom-0.4.9.dist-info/WHEEL
pycassodicom-0.4.9.dist-info/METADATA
pycassodicom-0.4.9.dist-info/RECORD
