Metadata-Version: 2.1
Name: pycassodicom
Version: 0.4.9
Summary: De-identify dicom images by blackening pixels
License: MIT
Author: barbara73
Author-email: barbara.jesacher@gmail.com
Requires-Python: >=3.9,<4.0
Classifier: License :: OSI Approved :: MIT License
Classifier: Programming Language :: Python :: 3
Classifier: Programming Language :: Python :: 3.9
Classifier: Programming Language :: Python :: 3.10
Classifier: Programming Language :: Python :: 3.11
